postgresdeploy/__init__.py
postgresdeploy/_check_constraint.py
postgresdeploy/_column.py
postgresdeploy/_functions.py
postgresdeploy/_helpers.py
postgresdeploy/_indexes.py
postgresdeploy/_primary_key.py
postgresdeploy/_tables.py
postgresdeploy/_triggers.py
postgresdeploy/_unique_constraint.py
postgresdeploy/_views.py
postgresdeploy/deploy.py
postgresdeploy/mirror.py
postgresdeploy-0.0.4.dist-info/METADATA
postgresdeploy-0.0.4.dist-info/WHEEL
postgresdeploy-0.0.4.dist-info/RECORD
